{
  "basics": {
    "name": "Nadine Soliman",
    "label": "PhD Student in Astrophysics, Caltech",
    "image": "prof_pic.jpg",
    "email": "nsoliman@caltech.edu",
    "url": "https://nadinesoliman.github.io/",
    "location": {
      "address": "1200 E California Blvd, MC 249-17",
      "postalCode": "CA 91125",
      "city": "Pasadena",
      "countryCode": "US",
      "region": "California"
    },
    "profiles": [
    ]
  },
  "education": [
{
      "institution": "California Institute of Technology, California, USA",
      "location": "California, USA",
      "url": "https://www.caltech.edu/",
      "area": "Astrophysics",
      "studyType": "PhD",
      "startDate": "2021-09-01",
      "endDate": "current"
    }
  ],
  "awards": [
    {
      "title": "Nobel Prize in Physics",
      "date": "1921-11-01",
      "awarder": "Royal Swedish Academy of Sciences",
      "url": "https://www.nobelprize.org/prizes/physics/1921/einstein/biographical/",
      "summary": "The Nobel Prizes are five separate prizes that, according to Alfred Nobel's will of 1895, are awarded to 'those who, during the preceding year, have conferred the greatest benefit to humankind.'"
    }
  ]
}
